torch_log_wmse/__init__.py
torch_log_wmse/constants.py
torch_log_wmse/filter_ir.pkl
torch_log_wmse/freq_weighting_filter.py
torch_log_wmse/metric.py
torch_log_wmse/utils.py
torch_log_wmse_audio_quality/__init__.py
torch_log_wmse_audio_quality/constants.py
torch_log_wmse_audio_quality/freq_weighting_filter.py
torch_log_wmse_audio_quality/metric.py
torch_log_wmse_audio_quality/utils.py
torch_log_wmse-0.3.1.dist-info/LICENSE
torch_log_wmse-0.3.1.dist-info/METADATA
torch_log_wmse-0.3.1.dist-info/WHEEL
torch_log_wmse-0.3.1.dist-info/top_level.txt
torch_log_wmse-0.3.1.dist-info/RECORD
