Metadata-Version: 2.1
Name: torch-log-wmse
Version: 0.3.1
Summary: logWMSE is an audio quality metric & loss function with support for digital silence target. Useful for training and evaluating audio source separation systems.
Home-page: https://github.com/crlandsc/torch-log-wmse
Author: Christopher Landschoot
Author-email: crlandschoot@gmail.com
License: Apache License 2.0
Project-URL: Bug Tracker, https://github.com/crlandsc/torch-log-wmse/issues
Classifier: Programming Language :: Python :: 3
Classifier: License :: OSI Approved :: Apache Software License
Classifier: Operating System :: OS Independent
Requires-Python: >=3.8
License-File: LICENSE
Requires-Dist: torch>=1.8.0
Requires-Dist: torchaudio>=1.8.0
Requires-Dist: numpy>=1.23.5
